LICENSE
MANIFEST.in
README.md
setup.py
lfrppy/__init__.py
lfrppy.egg-info/PKG-INFO
lfrppy.egg-info/SOURCES.txt
lfrppy.egg-info/dependency_links.txt
lfrppy.egg-info/entry_points.txt
lfrppy.egg-info/top_level.txt
lfrppy/bin/__init__.py
lfrppy/bin/frpc
lfrppy/bin/frps
lfrppy/core/__init__.py
lfrppy/core/cli.py
lfrppy/core/config_ops.py
lfrppy/core/entrypoints.py
lfrppy/core/listing.py
lfrppy/core/registry.py
lfrppy/core/systemd.py
lfrppy/frpc/__init__.py
lfrppy/frpc/_shared.py
lfrppy/frpc/cleanup.py
lfrppy/frpc/deploy.py
lfrppy/frpc/file_ops.py
lfrppy/frpc/listing.py
lfrppy/frpc/pwd.py
lfrppy/frpc/service.py
lfrppy/frps/__init__.py
lfrppy/frps/_shared.py
lfrppy/frps/cleanup.py
lfrppy/frps/deploy.py
lfrppy/frps/file_ops.py
lfrppy/frps/listing.py
lfrppy/frps/pwd.py
lfrppy/frps/service.py
lfrppy/resources/__init__.py
lfrppy/resources/__pycache__/__init__.cpython-312.pyc
lfrppy/resources/frpc/frpc_full_example.toml
lfrppy/resources/frpc/main.toml
lfrppy/resources/frpc/systemd/frpc@.service
lfrppy/resources/frps/frps_full_example.toml
lfrppy/resources/frps/main.toml
lfrppy/resources/frps/systemd/frps@.service