Metadata-Version: 2.4
Name: lfrppy
Version: 0.0.20
Summary: FRP deployment helpers
Author: Cai Jianping
Author-email: jpingcai@163.com
License: MIT Licence
Keywords: frp,tunnel,deployment
Platform: any
License-File: LICENSE
Dynamic: author
Dynamic: author-email
Dynamic: description
Dynamic: keywords
Dynamic: license
Dynamic: license-file
Dynamic: platform
Dynamic: summary
